enno
tests
