Metadata-Version: 1.1
Name: enno
Version: 0.0.6
Summary: Wrapper around Evernote's python client
Home-page: http://github.com/Jaymon/enno
Author: Jay Marcyes
Author-email: jay@marcyes.com
License: MIT
Platform: UNKNOWN
Classifier: Development Status :: 1 - Planning
Classifier: License :: OSI Approved :: MIT License
Classifier: Operating System :: OS Independent
Classifier: Programming Language :: Python :: 2.7
Classifier: Programming Language :: Python :: 3
